[
  {
    "wcaid": "2003BADI01",
    "name": "Frédérick Badie",
    "gender": "男",
    "country": "France",
    "province": "",
    "city": "",
    "result": "1:09.83",
    "competition": "Dutch Open 2005",
    "date": "2005-10-16"
  },
  {
    "wcaid": "2003HARD01",
    "name": "Chris Hardwick",
    "gender": "男",
    "country": "USA",
    "province": "",
    "city": "",
    "result": "1:06.08",
    "competition": "Caltech Dallas Summer competition 2005",
    "date": "2005-08-13"
  },
  {
    "wcaid": "2003AKIM01",
    "name": "Masayuki Akimoto (秋元正行)",
    "gender": "男",
    "country": "Japan",
    "province": "",
    "city": "",
    "result": "1:13.58",
    "competition": "Japanese Championship 2005",
    "date": "2005-09-03"
  },
  {
    "wcaid": "2004PEDA01",
    "name": "Sunil Pedapudi",
    "gender": "男",
    "country": "USA",
    "province": "",
    "city": "",
    "result": "3:07.53",
    "competition": "Caltech Fall competition 2005",
    "date": "2005-10-22"
  },
  {
    "wcaid": "2004BOUC01",
    "name": "Charles Bouchart",
    "gender": "男",
    "country": "France",
    "province": "",
    "city": "",
    "result": "1:26.64",
    "competition": "French Championship 2005",
    "date": "2005-04-22"
  },
  {
    "wcaid": "2004BORD01",
    "name": "Bertrand Bordage",
    "gender": "男",
    "country": "France",
    "province": "",
    "city": "",
    "result": "2:04.88",
    "competition": "French Championship 2005",
    "date": "2005-04-22"
  },
  {
    "wcaid": "2003KONI01",
    "name": "Katsuyuki Konishi (小西克幸)",
    "gender": "男",
    "country": "Japan",
    "province": "",
    "city": "",
    "result": "1:36.16",
    "competition": "Kyoto Rubik's Cube contest 2005",
    "date": "2005-07-10"
  },
  {
    "wcaid": "2005HAYA01",
    "name": "Yuki Hayashi (林祐樹)",
    "gender": "男",
    "country": "Japan",
    "province": "",
    "city": "",
    "result": "1:04.63",
    "competition": "Rubik's World Championship 2005",
    "date": "2005-11-05"
  },
  {
    "wcaid": "2004KODR01",
    "name": "Stefan Kodrnja",
    "gender": "男",
    "country": "Sweden",
    "province": "",
    "city": "",
    "result": "1:57.30",
    "competition": "Swedish Open 2005",
    "date": "2005-09-10"
  },
  {
    "wcaid": "2005TUSC01",
    "name": "Bill Tuscher",
    "gender": "男",
    "country": "USA",
    "province": "",
    "city": "",
    "result": "1:45.17",
    "competition": "Rutgers Fall competition 2005",
    "date": "2005-12-10"
  },
  {
    "wcaid": "2005CHRI02",
    "name": "Nathaniel Christian",
    "gender": "男",
    "country": "USA",
    "province": "",
    "city": "",
    "result": "1:59.77",
    "competition": "Rutgers Fall competition 2005",
    "date": "2005-12-10"
  },
  {
    "wcaid": "2005SZLA01",
    "name": "Chris Szlatenyi",
    "gender": "男",
    "country": "USA",
    "province": "",
    "city": "",
    "result": "3:04.44",
    "competition": "Rutgers Fall competition 2005",
    "date": "2005-12-10"
  },
  {
    "wcaid": "2005CAIB01",
    "name": "Brian Cai",
    "gender": "男",
    "country": "USA",
    "province": "",
    "city": "",
    "result": "3:05.97",
    "competition": "Rutgers Fall competition 2005",
    "date": "2005-12-10"
  },
  {
    "wcaid": "2005MUNJ01",
    "name": "Jonathan Mun",
    "gender": "男",
    "country": "USA",
    "province": "",
    "city": "",
    "result": "3:18.27",
    "competition": "Rutgers Fall competition 2005",
    "date": "2005-12-10"
  },
  {
    "wcaid": "2005BEDA01",
    "name": "Scott Bedard",
    "gender": "男",
    "country": "USA",
    "province": "",
    "city": "",
    "result": "3:46.79",
    "competition": "Rutgers Fall competition 2005",
    "date": "2005-12-10"
  },
  {
    "wcaid": "2005SCIB01",
    "name": "Richard Scibetti",
    "gender": "男",
    "country": "USA",
    "province": "",
    "city": "",
    "result": "5:53.99",
    "competition": "Rutgers Fall competition 2005",
    "date": "2005-12-10"
  },
  {
    "wcaid": "2005PROD01",
    "name": "Mitko Prodanov",
    "gender": "男",
    "country": "Hungary",
    "province": "",
    "city": "",
    "result": "2:22.33",
    "competition": "Hungarian Championship 2005",
    "date": "2005-11-19"
  },
  {
    "wcaid": "2005HANT01",
    "name": "Norbert Hantos",
    "gender": "男",
    "country": "Hungary",
    "province": "",
    "city": "",
    "result": "3:35.46",
    "competition": "Hungarian Championship 2005",
    "date": "2005-11-19"
  },
  {
    "wcaid": "2005SZIG01",
    "name": "Máté Szigetvári",
    "gender": "男",
    "country": "Hungary",
    "province": "",
    "city": "",
    "result": "3:41.43",
    "competition": "Hungarian Championship 2005",
    "date": "2005-11-19"
  },
  {
    "wcaid": "2005CSIL01",
    "name": "Péter Csillag",
    "gender": "男",
    "country": "Hungary",
    "province": "",
    "city": "",
    "result": "4:41.59",
    "competition": "Hungarian Championship 2005",
    "date": "2005-11-19"
  },
  {
    "wcaid": "2005ROZS01",
    "name": "Dávid Rózsa",
    "gender": "男",
    "country": "Hungary",
    "province": "",
    "city": "",
    "result": "4:57.61",
    "competition": "Hungarian Championship 2005",
    "date": "2005-11-19"
  },
  {
    "wcaid": "2005RITE01",
    "name": "Attila Ritecz",
    "gender": "男",
    "country": "Hungary",
    "province": "",
    "city": "",
    "result": "5:10.33",
    "competition": "Hungarian Championship 2005",
    "date": "2005-11-19"
  },
  {
    "wcaid": "2005IVAN01",
    "name": "Tamás Iványi",
    "gender": "男",
    "country": "Hungary",
    "province": "",
    "city": "",
    "result": "6:25.94",
    "competition": "Hungarian Championship 2005",
    "date": "2005-11-19"
  },
  {
    "wcaid": "2005SOVE01",
    "name": "András Sövény",
    "gender": "男",
    "country": "Hungary",
    "province": "",
    "city": "",
    "result": "6:35.74",
    "competition": "Hungarian Championship 2005",
    "date": "2005-11-19"
  },
  {
    "wcaid": "2005CUES01",
    "name": "Alberto Cuesta",
    "gender": "男",
    "country": "Spain",
    "province": "",
    "city": "",
    "result": "3:47.11",
    "competition": "Spanish Championship 2005",
    "date": "2005-12-03"
  },
  {
    "wcaid": "2004JUAN01",
    "name": "Raul de Juan Tejeda",
    "gender": "男",
    "country": "Spain",
    "province": "",
    "city": "",
    "result": "4:33.84",
    "competition": "Spanish Championship 2005",
    "date": "2005-12-03"
  },
  {
    "wcaid": "2004GAIT01",
    "name": "Parker Gaitley",
    "gender": "男",
    "country": "USA",
    "province": "",
    "city": "",
    "result": "1:59.72",
    "competition": "Caltech Fall competition 2005",
    "date": "2005-10-22"
  },
  {
    "wcaid": "2005LWIN01",
    "name": "Kyawkyaw Lwin",
    "gender": "男",
    "country": "USA",
    "province": "",
    "city": "",
    "result": "2:09.60",
    "competition": "Caltech Fall competition 2005",
    "date": "2005-10-22"
  },
  {
    "wcaid": "2004LINP01",
    "name": "Paul Lin",
    "gender": "男",
    "country": "USA",
    "province": "",
    "city": "",
    "result": "2:51.58",
    "competition": "Caltech Fall competition 2005",
    "date": "2005-10-22"
  },
  {
    "wcaid": "2005GAND01",
    "name": "Michał Gandor",
    "gender": "男",
    "country": "Poland",
    "province": "",
    "city": "",
    "result": "2:15.20",
    "competition": "Polish Open 2005",
    "date": "2005-09-18"
  },
  {
    "wcaid": "2004JELI01",
    "name": "Josef Jelínek",
    "gender": "男",
    "country": "Czech Republic",
    "province": "",
    "city": "",
    "result": "2:58.17",
    "competition": "Polish Open 2005",
    "date": "2005-09-18"
  },
  {
    "wcaid": "2005DURK01",
    "name": "Remigiusz Durka",
    "gender": "男",
    "country": "Poland",
    "province": "",
    "city": "",
    "result": "3:33.78",
    "competition": "Polish Open 2005",
    "date": "2005-09-18"
  },
  {
    "wcaid": "2004GALL01",
    "name": "Antonio Gallego Zambrano",
    "gender": "男",
    "country": "Spain",
    "province": "",
    "city": "",
    "result": "4:58.91",
    "competition": "Polish Open 2005",
    "date": "2005-09-18"
  },
  {
    "wcaid": "2005PETA01",
    "name": "Dariusz Peta",
    "gender": "男",
    "country": "Poland",
    "province": "",
    "city": "",
    "result": "5:35.58",
    "competition": "Polish Open 2005",
    "date": "2005-09-18"
  },
  {
    "wcaid": "2005BORY01",
    "name": "Krzysztof Boryczko",
    "gender": "男",
    "country": "Poland",
    "province": "",
    "city": "",
    "result": "5:37.49",
    "competition": "Polish Open 2005",
    "date": "2005-09-18"
  },
  {
    "wcaid": "2005SOES01",
    "name": "Jeff Soesbe",
    "gender": "男",
    "country": "USA",
    "province": "",
    "city": "",
    "result": "2:37.05",
    "competition": "Northern California Fall Open 2005",
    "date": "2005-09-17"
  },
  {
    "wcaid": "2003ATKI01",
    "name": "Michael Atkinson",
    "gender": "男",
    "country": "USA",
    "province": "",
    "city": "",
    "result": "3:19.44",
    "competition": "Idaho Open 2005",
    "date": "2005-09-17"
  },
  {
    "wcaid": "2005HILL01",
    "name": "Johan Hillerström",
    "gender": "男",
    "country": "Sweden",
    "province": "",
    "city": "",
    "result": "1:57.25",
    "competition": "Swedish Open 2005",
    "date": "2005-09-10"
  },
  {
    "wcaid": "2005CHOS01",
    "name": "Manabu Choshi (町支学)",
    "gender": "男",
    "country": "Japan",
    "province": "",
    "city": "",
    "result": "2:03.97",
    "competition": "Japanese Championship 2005",
    "date": "2005-09-03"
  },
  {
    "wcaid": "2005MISH01",
    "name": "Yuzuru Mishima (三島譲)",
    "gender": "男",
    "country": "Japan",
    "province": "",
    "city": "",
    "result": "2:20.68",
    "competition": "Japanese Championship 2005",
    "date": "2005-09-03"
  },
  {
    "wcaid": "2005KURI01",
    "name": "Ryo Kurihara (栗原涼)",
    "gender": "男",
    "country": "Japan",
    "province": "",
    "city": "",
    "result": "2:43.55",
    "competition": "Japanese Championship 2005",
    "date": "2005-09-03"
  },
  {
    "wcaid": "2005TAKA01",
    "name": "Hideaki Takahashi (高橋英明)",
    "gender": "男",
    "country": "Japan",
    "province": "",
    "city": "",
    "result": "3:20.93",
    "competition": "Japanese Championship 2005",
    "date": "2005-09-03"
  },
  {
    "wcaid": "2004BEST01",
    "name": "Jorge Best",
    "gender": "男",
    "country": "Mexico",
    "province": "",
    "city": "",
    "result": "4:15.21",
    "competition": "Caltech Dallas Summer competition 2005",
    "date": "2005-08-13"
  },
  {
    "wcaid": "2005HIRA02",
    "name": "Toshinobu Hirayama (平山寿信)",
    "gender": "男",
    "country": "Japan",
    "province": "",
    "city": "",
    "result": "2:20.16",
    "competition": "Kyoto Rubik's Cube contest 2005",
    "date": "2005-07-10"
  },
  {
    "wcaid": "2005NODA01",
    "name": "Satoru Noda (野田悟)",
    "gender": "男",
    "country": "Japan",
    "province": "",
    "city": "",
    "result": "2:59.44",
    "competition": "Kyoto Rubik's Cube contest 2005",
    "date": "2005-07-10"
  },
  {
    "wcaid": "2004NILS01",
    "name": "Dennis Nilsson",
    "gender": "男",
    "country": "Sweden",
    "province": "",
    "city": "",
    "result": "3:29.23",
    "competition": "Chalmers Open 2005",
    "date": "2005-06-05"
  },
  {
    "wcaid": "2005BRYN01",
    "name": "Lucas Brynte",
    "gender": "男",
    "country": "Sweden",
    "province": "",
    "city": "",
    "result": "3:34.47",
    "competition": "Chalmers Open 2005",
    "date": "2005-06-05"
  },
  {
    "wcaid": "2005KJEL01",
    "name": "Carl-Johan Kjellander",
    "gender": "男",
    "country": "Sweden",
    "province": "",
    "city": "",
    "result": "4:21.50",
    "competition": "Chalmers Open 2005",
    "date": "2005-06-05"
  },
  {
    "wcaid": "2005LEWI01",
    "name": "Quinn Lewis",
    "gender": "男",
    "country": "USA",
    "province": "",
    "city": "",
    "result": "1:49.46",
    "competition": "Horace Mann Spring competition 2005",
    "date": "2005-05-28"
  },
  {
    "wcaid": "2005SERV01",
    "name": "Grégory Servaud",
    "gender": "男",
    "country": "France",
    "province": "",
    "city": "",
    "result": "2:23.85",
    "competition": "French Championship 2005",
    "date": "2005-04-22"
  },
  {
    "wcaid": "2004CARA01",
    "name": "Jibril Caratini-Sotto",
    "gender": "男",
    "country": "France",
    "province": "",
    "city": "",
    "result": "3:02.40",
    "competition": "French Championship 2005",
    "date": "2005-04-22"
  },
  {
    "wcaid": "2004WONG01",
    "name": "Chun Hei Uwe Wong",
    "gender": "男",
    "country": "China",
    "province": "香港",
    "city": "香港",
    "result": "2:06.77",
    "competition": "Caltech Spring competition 2005",
    "date": "2005-04-16"
  },
  {
    "wcaid": "2004BERG01",
    "name": "Mattias Berglund",
    "gender": "男",
    "country": "Sweden",
    "province": "",
    "city": "",
    "result": "2:20.65",
    "competition": "SveKub Annual Meeting competition 2005",
    "date": "2005-03-27"
  },
  {
    "wcaid": "2004BISC01",
    "name": "Thomas Bischof",
    "gender": "男",
    "country": "USA",
    "province": "",
    "city": "",
    "result": "2:22.50",
    "competition": "Caltech Winter competition 2005",
    "date": "2005-01-15"
  }
]