[
  {
    "wcaid": "2008CHAN09",
    "name": "Hsuan Chang (張璿)",
    "gender": "男",
    "country": "China",
    "province": "台湾",
    "city": "台湾",
    "result": "4:15.56",
    "competition": "Taiwan Winter Open 2010",
    "date": "2010-02-06"
  },
  {
    "wcaid": "2008CHEN06",
    "name": "Han-Cyun Chen (陳翰群)",
    "gender": "男",
    "country": "China",
    "province": "台湾",
    "city": "台湾",
    "result": "3:50.90",
    "competition": "Taiwan Big Cube Day 2010",
    "date": "2010-06-05"
  },
  {
    "wcaid": "2009KUAN01",
    "name": "Kuan-Yu Chen (陳冠宇)",
    "gender": "男",
    "country": "China",
    "province": "台湾",
    "city": "台湾",
    "result": "6:45.05",
    "competition": "Taiwan Winter Open 2010",
    "date": "2010-02-06"
  },
  {
    "wcaid": "2006CHEN03",
    "name": "Kuan-Yu Chen (陳冠宇)",
    "gender": "男",
    "country": "China",
    "province": "台湾",
    "city": "台湾",
    "result": "7:01.74",
    "competition": "Taiwan Big Cube Day 2010",
    "date": "2010-06-05"
  },
  {
    "wcaid": "2007TONG01",
    "name": "Wei-Ming Tong (唐偉銘)",
    "gender": "男",
    "country": "China",
    "province": "台湾",
    "city": "台湾",
    "result": "7:30.81",
    "competition": "Taiwan Big Cube Day 2010",
    "date": "2010-06-05"
  },
  {
    "wcaid": "2008KAOC01",
    "name": "Chung-Chern Kao (高中宸)",
    "gender": "男",
    "country": "China",
    "province": "台湾",
    "city": "台湾",
    "result": "5:49.27",
    "competition": "Taiwan Big Cube Day 2010",
    "date": "2010-06-05"
  },
  {
    "wcaid": "2009HUAN03",
    "name": "Wei-Hao Huang (黃偉豪)",
    "gender": "男",
    "country": "China",
    "province": "台湾",
    "city": "台湾",
    "result": "5:10.31",
    "competition": "Taiwan Winter Open 2010",
    "date": "2010-02-06"
  },
  {
    "wcaid": "2007NELS02",
    "name": "Gavin Nelson",
    "gender": "男",
    "country": "USA",
    "province": "",
    "city": "",
    "result": "6:57.28",
    "competition": "United States Rubik's Cube Championships 2010",
    "date": "2010-08-06"
  },
  {
    "wcaid": "2008SMIT04",
    "name": "Maarten Smit",
    "gender": "男",
    "country": "Netherlands",
    "province": "",
    "city": "",
    "result": "4:33.59",
    "competition": "Belgian Open 2010",
    "date": "2010-05-22"
  },
  {
    "wcaid": "2008DIEW01",
    "name": "Jens Diewald",
    "gender": "男",
    "country": "Germany",
    "province": "",
    "city": "",
    "result": "7:17.56",
    "competition": "German Nationals 2010",
    "date": "2010-09-11"
  },
  {
    "wcaid": "2008CABA03",
    "name": "Jakub Cabaj",
    "gender": "男",
    "country": "Poland",
    "province": "",
    "city": "",
    "result": "4:38.18",
    "competition": "V-CUBE Spiel 2010",
    "date": "2010-10-23"
  },
  {
    "wcaid": "2008HANK01",
    "name": "Kanneti Sae Han (คันธ์เนตี แซ่ห่าน)",
    "gender": "男",
    "country": "France",
    "province": "",
    "city": "",
    "result": "5:17.96",
    "competition": "Barcelona Rubik's Summer Open 2010",
    "date": "2010-07-09"
  },
  {
    "wcaid": "2007COOP01",
    "name": "Charlie Cooper",
    "gender": "女",
    "country": "United Kingdom",
    "province": "",
    "city": "",
    "result": "6:40.97",
    "competition": "Bristol Spring 2010",
    "date": "2010-03-27"
  },
  {
    "wcaid": "2008CASQ01",
    "name": "Jemco Casquejo",
    "gender": "男",
    "country": "Philippines",
    "province": "",
    "city": "",
    "result": "6:12.93",
    "competition": "Cebu Open 2010",
    "date": "2010-12-07"
  },
  {
    "wcaid": "2008LEEY01",
    "name": "Yi Lee (李屹)",
    "gender": "男",
    "country": "China",
    "province": "台湾",
    "city": "台湾",
    "result": "5:13.97",
    "competition": "Taiwan Big Cube Day 2010",
    "date": "2010-06-05"
  },
  {
    "wcaid": "2007RUIZ01",
    "name": "Uriel Gayosso Ruiz",
    "gender": "男",
    "country": "Mexico",
    "province": "",
    "city": "",
    "result": "6:00.78",
    "competition": "Guadalajara Open 2010",
    "date": "2010-07-24"
  },
  {
    "wcaid": "2007BODO01",
    "name": "Bertalan Bodor",
    "gender": "男",
    "country": "Hungary",
    "province": "",
    "city": "",
    "result": "6:14.09",
    "competition": "Benelux Open 2010",
    "date": "2010-02-20"
  },
  {
    "wcaid": "2009BAUM01",
    "name": "Conor Baumann",
    "gender": "男",
    "country": "Ireland",
    "province": "",
    "city": "",
    "result": "11:28.00",
    "competition": "Madrid Open Rubik 2010",
    "date": "2010-10-30"
  },
  {
    "wcaid": "2007RIBE01",
    "name": "Rodrigo Ybarra de Oliveira Ribeiro",
    "gender": "男",
    "country": "Brazil",
    "province": "",
    "city": "",
    "result": "14:34.00",
    "competition": "SESC Santos 2010",
    "date": "2010-07-23"
  },
  {
    "wcaid": "2009PETI01",
    "name": "Loïc Petit",
    "gender": "男",
    "country": "France",
    "province": "",
    "city": "",
    "result": "7:31.94",
    "competition": "Toulouse Open 2010",
    "date": "2010-01-23"
  },
  {
    "wcaid": "2008LEME01",
    "name": "Pierre Lemerle",
    "gender": "男",
    "country": "France",
    "province": "",
    "city": "",
    "result": "8:39.72",
    "competition": "Naoned Open 2010",
    "date": "2010-10-23"
  },
  {
    "wcaid": "2007CHOW01",
    "name": "Stephanie Chow",
    "gender": "女",
    "country": "USA",
    "province": "",
    "city": "",
    "result": "7:09.88",
    "competition": "United States Rubik's Cube Championships 2010",
    "date": "2010-08-06"
  },
  {
    "wcaid": "2007TIIN01",
    "name": "Teemu Tiinanen",
    "gender": "男",
    "country": "Finland",
    "province": "",
    "city": "",
    "result": "7:20.34",
    "competition": "Norwegian Open 2010",
    "date": "2010-02-13"
  },
  {
    "wcaid": "2008SIMO02",
    "name": "Nicolò Simone",
    "gender": "男",
    "country": "Italy",
    "province": "",
    "city": "",
    "result": "7:59.81",
    "competition": "Cube 'n Roll Italian Open 2010",
    "date": "2010-06-05"
  },
  {
    "wcaid": "2009PAIV01",
    "name": "Christian Paiva",
    "gender": "男",
    "country": "Canada",
    "province": "",
    "city": "",
    "result": "6:55.53",
    "competition": "canadianCUBING CUBEcentric 2010",
    "date": "2010-05-15"
  },
  {
    "wcaid": "2008BORU01",
    "name": "Holger Stadel Borum",
    "gender": "男",
    "country": "Denmark",
    "province": "",
    "city": "",
    "result": "4:43.86",
    "competition": "European Rubik's Cube Championship 2010",
    "date": "2010-10-01"
  },
  {
    "wcaid": "2008INGL01",
    "name": "Wojciech Inglot",
    "gender": "男",
    "country": "Poland",
    "province": "",
    "city": "",
    "result": "8:16.03",
    "competition": "Pabianice Open 2010",
    "date": "2010-09-18"
  },
  {
    "wcaid": "2009SMAR01",
    "name": "Jan Smarschevski",
    "gender": "男",
    "country": "Germany",
    "province": "",
    "city": "",
    "result": "4:10.19",
    "competition": "Munich Open 2010",
    "date": "2010-10-09"
  },
  {
    "wcaid": "2009AREN01",
    "name": "Koen Arens",
    "gender": "男",
    "country": "Netherlands",
    "province": "",
    "city": "",
    "result": "6:39.40",
    "competition": "Benelux Open 2010",
    "date": "2010-02-20"
  },
  {
    "wcaid": "2008VECS01",
    "name": "Márk Vecsernyés",
    "gender": "男",
    "country": "Hungary",
    "province": "",
    "city": "",
    "result": "6:34.77",
    "competition": "Hungarian Open 2010",
    "date": "2010-09-03"
  },
  {
    "wcaid": "2008MIHA01",
    "name": "Zalán Mihály",
    "gender": "男",
    "country": "Hungary",
    "province": "",
    "city": "",
    "result": "6:10.66",
    "competition": "Hungarian Open 2010",
    "date": "2010-09-03"
  },
  {
    "wcaid": "2009BUIT01",
    "name": "Karsten Buitkamp",
    "gender": "男",
    "country": "Germany",
    "province": "",
    "city": "",
    "result": "9:25.19",
    "competition": "V-CUBE Spiel 2010",
    "date": "2010-10-23"
  },
  {
    "wcaid": "2009KOBA04",
    "name": "Rodrigo Kenji Asato Kobayashi",
    "gender": "男",
    "country": "Brazil",
    "province": "",
    "city": "",
    "result": "5:14.09",
    "competition": "SESC Santos 2010",
    "date": "2010-07-23"
  },
  {
    "wcaid": "2008GMYR01",
    "name": "Michał Gmyrek",
    "gender": "男",
    "country": "Poland",
    "province": "",
    "city": "",
    "result": "6:42.93",
    "competition": "Polish Open 2010",
    "date": "2010-02-27"
  },
  {
    "wcaid": "2009ASBR01",
    "name": "Oskar Åsbrink",
    "gender": "男",
    "country": "Sweden",
    "province": "",
    "city": "",
    "result": "6:29.08",
    "competition": "Swedish Open 2010",
    "date": "2010-09-11"
  },
  {
    "wcaid": "2009HAWK01",
    "name": "Clarke Hawkinson",
    "gender": "男",
    "country": "USA",
    "province": "",
    "city": "",
    "result": "10:05.00",
    "competition": "Utah Summer 2010",
    "date": "2010-08-28"
  },
  {
    "wcaid": "2008QINF01",
    "name": "Fang Qin (秦方)",
    "gender": "男",
    "country": "China",
    "province": "神手谷",
    "city": "神手谷",
    "result": "6:20.55",
    "competition": "Beijing Side Events Supplement 2010",
    "date": "2010-05-23"
  },
  {
    "wcaid": "2008SONG01",
    "name": "Ge Song (宋鸽)",
    "gender": "男",
    "country": "China",
    "province": "神手谷",
    "city": "神手谷",
    "result": "6:45.83",
    "competition": "Beijing No Cubes 2010",
    "date": "2010-11-28"
  },
  {
    "wcaid": "2009LUNA01",
    "name": "Luigi Lunardon",
    "gender": "男",
    "country": "Italy",
    "province": "",
    "city": "",
    "result": "12:18.00",
    "competition": "S.P.Q.R. Italian Rubik's Cube Championship 2010",
    "date": "2010-07-26"
  },
  {
    "wcaid": "2010CHAW01",
    "name": "Kanapol Chawawiwat",
    "gender": "男",
    "country": "Thailand",
    "province": "",
    "city": "",
    "result": "9:25.97",
    "competition": "Bangkok Open 2010",
    "date": "2010-01-09"
  },
  {
    "wcaid": "2009LEIS01",
    "name": "Jonathan Leistner",
    "gender": "男",
    "country": "Germany",
    "province": "",
    "city": "",
    "result": "4:27.67",
    "competition": "German Open 2010",
    "date": "2010-04-17"
  },
  {
    "wcaid": "2009KURT01",
    "name": "Marwin-Peter Kurth",
    "gender": "男",
    "country": "Germany",
    "province": "",
    "city": "",
    "result": "5:46.86",
    "competition": "Aachen Open 2010",
    "date": "2010-01-16"
  },
  {
    "wcaid": "2008LOMB01",
    "name": "Pasquale Lombardozzi",
    "gender": "男",
    "country": "Italy",
    "province": "",
    "city": "",
    "result": "6:50.75",
    "competition": "Cologne Open 2010",
    "date": "2010-06-12"
  },
  {
    "wcaid": "2009LERN01",
    "name": "David Lerner",
    "gender": "男",
    "country": "Germany",
    "province": "",
    "city": "",
    "result": "8:45.47",
    "competition": "Aachen Open 2010",
    "date": "2010-01-16"
  },
  {
    "wcaid": "2009ASSM01",
    "name": "Carl Assmann",
    "gender": "男",
    "country": "Germany",
    "province": "",
    "city": "",
    "result": "9:01.52",
    "competition": "Aachen Open 2010",
    "date": "2010-01-16"
  },
  {
    "wcaid": "2009SPIE01",
    "name": "Niklas Spies",
    "gender": "男",
    "country": "Germany",
    "province": "",
    "city": "",
    "result": "6:59.81",
    "competition": "Alania Open 2010",
    "date": "2010-06-26"
  },
  {
    "wcaid": "2010SEID01",
    "name": "Jörg Seidler",
    "gender": "男",
    "country": "Germany",
    "province": "",
    "city": "",
    "result": "11:12.00",
    "competition": "Cologne Open 2010",
    "date": "2010-06-12"
  },
  {
    "wcaid": "2008CHAN12",
    "name": "Ahn Chang-Bae",
    "gender": "男",
    "country": "Korea",
    "province": "",
    "city": "",
    "result": "6:19.77",
    "competition": "Korea Cube Championship 2010",
    "date": "2010-01-23"
  },
  {
    "wcaid": "2006SEUL01",
    "name": "Son Seul-Gi",
    "gender": "女",
    "country": "Korea",
    "province": "",
    "city": "",
    "result": "6:47.80",
    "competition": "Korea Cube Championship 2010",
    "date": "2010-01-23"
  },
  {
    "wcaid": "2008BUMS01",
    "name": "Moon Bum-Seok",
    "gender": "男",
    "country": "Korea",
    "province": "",
    "city": "",
    "result": "7:05.63",
    "competition": "Korea Cube Championship 2010",
    "date": "2010-01-23"
  },
  {
    "wcaid": "2009ROCH01",
    "name": "Julien Rochette",
    "gender": "男",
    "country": "France",
    "province": "",
    "city": "",
    "result": "4:53.03",
    "competition": "Naoned Open 2010",
    "date": "2010-10-23"
  },
  {
    "wcaid": "2008PIQU01",
    "name": "Jordi Piqueras Gómez",
    "gender": "男",
    "country": "Spain",
    "province": "",
    "city": "",
    "result": "9:34.10",
    "competition": "Toulouse Open 2010",
    "date": "2010-01-23"
  },
  {
    "wcaid": "2009VROO01",
    "name": "Bradley Vrooman",
    "gender": "男",
    "country": "USA",
    "province": "",
    "city": "",
    "result": "5:24.40",
    "competition": "Utah Summer 2010",
    "date": "2010-08-28"
  },
  {
    "wcaid": "2010YUZO01",
    "name": "Zhong-Lun Yu (余宗倫)",
    "gender": "男",
    "country": "China",
    "province": "台湾",
    "city": "台湾",
    "result": "6:26.47",
    "competition": "Taiwan Winter Open 2010",
    "date": "2010-02-06"
  },
  {
    "wcaid": "2009CHEN37",
    "name": "Liu Cheng-Wei (劉正威)",
    "gender": "男",
    "country": "China",
    "province": "台湾",
    "city": "台湾",
    "result": "7:32.13",
    "competition": "Taiwan Winter Open 2010",
    "date": "2010-02-06"
  },
  {
    "wcaid": "2007SUNT01",
    "name": "Timothy Sun",
    "gender": "男",
    "country": "USA",
    "province": "",
    "city": "",
    "result": "5:43.15",
    "competition": "Drexel Winter 2010",
    "date": "2010-02-06"
  },
  {
    "wcaid": "2009HOVE01",
    "name": "Edvard Hove",
    "gender": "男",
    "country": "Norway",
    "province": "",
    "city": "",
    "result": "6:26.06",
    "competition": "Norwegian Open 2010",
    "date": "2010-02-13"
  },
  {
    "wcaid": "2009ANFI01",
    "name": "Henrik Anfinsen",
    "gender": "男",
    "country": "Norway",
    "province": "",
    "city": "",
    "result": "6:36.80",
    "competition": "Norwegian Open 2010",
    "date": "2010-02-13"
  },
  {
    "wcaid": "2009MAGN02",
    "name": "Hilmar Magnusson",
    "gender": "男",
    "country": "Iceland",
    "province": "",
    "city": "",
    "result": "7:27.65",
    "competition": "Norwegian Open 2010",
    "date": "2010-02-13"
  },
  {
    "wcaid": "2009ABSA01",
    "name": "Kristoffer Absalonsen",
    "gender": "男",
    "country": "Norway",
    "province": "",
    "city": "",
    "result": "8:15.53",
    "competition": "Norwegian Open 2010",
    "date": "2010-02-13"
  },
  {
    "wcaid": "2009ELIN01",
    "name": "Viktor Elinder",
    "gender": "男",
    "country": "Sweden",
    "province": "",
    "city": "",
    "result": "12:49.00",
    "competition": "Swedish Open 2010",
    "date": "2010-09-11"
  },
  {
    "wcaid": "2008NIED01",
    "name": "Jeremi Niedziela",
    "gender": "男",
    "country": "Poland",
    "province": "",
    "city": "",
    "result": "8:36.93",
    "competition": "Polish Open 2010",
    "date": "2010-02-27"
  },
  {
    "wcaid": "2010DELL01",
    "name": "Claus Dellgreen",
    "gender": "男",
    "country": "Denmark",
    "province": "",
    "city": "",
    "result": "8:56.75",
    "competition": "Danish Open 2010",
    "date": "2010-02-27"
  },
  {
    "wcaid": "2010THOM01",
    "name": "Mads Thomassen",
    "gender": "男",
    "country": "Denmark",
    "province": "",
    "city": "",
    "result": "9:09.69",
    "competition": "Danish Open 2010",
    "date": "2010-02-27"
  },
  {
    "wcaid": "2006LECK01",
    "name": "Mimmi Leckius",
    "gender": "女",
    "country": "Sweden",
    "province": "",
    "city": "",
    "result": "10:20.00",
    "competition": "Swedish Open 2010",
    "date": "2010-09-11"
  },
  {
    "wcaid": "2009KRIS02",
    "name": "Martin Kristensen",
    "gender": "男",
    "country": "Denmark",
    "province": "",
    "city": "",
    "result": "16:47.00",
    "competition": "Danish Open 2010",
    "date": "2010-02-27"
  },
  {
    "wcaid": "2008MORA02",
    "name": "Jorge Morata Carrasco",
    "gender": "男",
    "country": "Spain",
    "province": "",
    "city": "",
    "result": "7:37.56",
    "competition": "Madrid Open Rubik 2010",
    "date": "2010-10-30"
  },
  {
    "wcaid": "2008PERE02",
    "name": "Francisco Pérez Padilla",
    "gender": "男",
    "country": "Spain",
    "province": "",
    "city": "",
    "result": "15:10.00",
    "competition": "Madrid Open 2010",
    "date": "2010-03-13"
  },
  {
    "wcaid": "2010ESPI01",
    "name": "Javier Espinosa García",
    "gender": "男",
    "country": "Spain",
    "province": "",
    "city": "",
    "result": "23:24.00",
    "competition": "Barcelona Rubik's Summer Open 2010",
    "date": "2010-07-09"
  },
  {
    "wcaid": "2009BRUS01",
    "name": "Berit Brüster",
    "gender": "女",
    "country": "Germany",
    "province": "",
    "city": "",
    "result": "8:27.66",
    "competition": "German Open 2010",
    "date": "2010-04-17"
  },
  {
    "wcaid": "2010MARI01",
    "name": "Esteban Marin",
    "gender": "男",
    "country": "Colombia",
    "province": "",
    "city": "",
    "result": "15:35.00",
    "competition": "Montpellier Open 2010",
    "date": "2010-03-20"
  },
  {
    "wcaid": "2009OCAM01",
    "name": "Janilo Ocampo",
    "gender": "男",
    "country": "Philippines",
    "province": "",
    "city": "",
    "result": "13:04.00",
    "competition": "Bulacan Open 2010",
    "date": "2010-04-10"
  },
  {
    "wcaid": "2009KORB02",
    "name": "Lasse Korbanka",
    "gender": "男",
    "country": "Germany",
    "province": "",
    "city": "",
    "result": "4:17.03",
    "competition": "V-CUBE Spiel 2010",
    "date": "2010-10-23"
  },
  {
    "wcaid": "2009KASU01",
    "name": "Sanio Kasumovic",
    "gender": "男",
    "country": "Austria",
    "province": "",
    "city": "",
    "result": "12:39.00",
    "competition": "Cologne Open 2010",
    "date": "2010-06-12"
  },
  {
    "wcaid": "2009RYAB01",
    "name": "Sergey Ryabko",
    "gender": "男",
    "country": "Russia",
    "province": "",
    "city": "",
    "result": "6:52.05",
    "competition": "Russia Open 2010",
    "date": "2010-04-24"
  },
  {
    "wcaid": "2008DING02",
    "name": "Jian Ding (丁健)",
    "gender": "男",
    "country": "China",
    "province": "神手谷",
    "city": "神手谷",
    "result": "6:19.36",
    "competition": "Nanjing Spring Open 2010",
    "date": "2010-04-25"
  },
  {
    "wcaid": "2009SUNW01",
    "name": "Weiwei Sun (孙巍巍)",
    "gender": "男",
    "country": "China",
    "province": "北京",
    "city": "北京",
    "result": "8:25.46",
    "competition": "Nanjing Spring Open 2010",
    "date": "2010-04-25"
  },
  {
    "wcaid": "2009CHEN50",
    "name": "Kaiyuan Chen (陈恺垣)",
    "gender": "男",
    "country": "China",
    "province": "江苏",
    "city": "南京",
    "result": "8:26.68",
    "competition": "Nanjing Spring Open 2010",
    "date": "2010-04-25"
  },
  {
    "wcaid": "2009WANG13",
    "name": "Yuxuan Wang (王宇轩)",
    "gender": "男",
    "country": "China",
    "province": "北京",
    "city": "北京",
    "result": "8:46.11",
    "competition": "Nanjing Spring Open 2010",
    "date": "2010-04-25"
  },
  {
    "wcaid": "2009SPRI01",
    "name": "Alexander Springhorn",
    "gender": "男",
    "country": "Germany",
    "province": "",
    "city": "",
    "result": "6:45.00",
    "competition": "V-CUBE Spiel 2010",
    "date": "2010-10-23"
  },
  {
    "wcaid": "2010SAMA01",
    "name": "Olivier Samann",
    "gender": "男",
    "country": "France",
    "province": "",
    "city": "",
    "result": "11:10.00",
    "competition": "Belgian Open 2010",
    "date": "2010-05-22"
  },
  {
    "wcaid": "2009WANG27",
    "name": "Xinye Wang (王鑫晔)",
    "gender": "男",
    "country": "China",
    "province": "北京",
    "city": "北京",
    "result": "8:38.22",
    "competition": "Inner Mongolia 2010",
    "date": "2010-07-24"
  },
  {
    "wcaid": "2010XUEF01",
    "name": "Fei Xue (薛非)",
    "gender": "男",
    "country": "China",
    "province": "神手谷",
    "city": "神手谷",
    "result": "9:24.88",
    "competition": "Beijing No Cubes 2010",
    "date": "2010-11-28"
  },
  {
    "wcaid": "2010LEIJ01",
    "name": "Jianlin Lei (雷建麟)",
    "gender": "男",
    "country": "China",
    "province": "神手谷",
    "city": "神手谷",
    "result": "8:06.30",
    "competition": "Taiyuan 2010",
    "date": "2010-05-30"
  },
  {
    "wcaid": "2009DUAN01",
    "name": "Linqiong Duan (段琳琼)",
    "gender": "女",
    "country": "China",
    "province": "山西",
    "city": "太原",
    "result": "25:19.00",
    "competition": "Taiyuan 2010",
    "date": "2010-05-30"
  },
  {
    "wcaid": "2009CHEN17",
    "name": "Jie-Ju Chen (陳玠儒)",
    "gender": "男",
    "country": "China",
    "province": "台湾",
    "city": "台湾",
    "result": "5:15.41",
    "competition": "Taiwan Big Cube Day 2010",
    "date": "2010-06-05"
  },
  {
    "wcaid": "2010HUAN04",
    "name": "Yu-Huan Huang (黃宇瑍)",
    "gender": "男",
    "country": "China",
    "province": "台湾",
    "city": "台湾",
    "result": "10:03.00",
    "competition": "Taiwan Big Cube Day 2010",
    "date": "2010-06-05"
  },
  {
    "wcaid": "2010BAHR01",
    "name": "Andreas Bahr",
    "gender": "男",
    "country": "Germany",
    "province": "",
    "city": "",
    "result": "6:17.46",
    "competition": "Cologne Open 2010",
    "date": "2010-06-12"
  },
  {
    "wcaid": "2009HERZ01",
    "name": "Florian Herzog",
    "gender": "男",
    "country": "Austria",
    "province": "",
    "city": "",
    "result": "8:54.84",
    "competition": "Austrian Open 2010",
    "date": "2010-07-31"
  },
  {
    "wcaid": "2008BLOH02",
    "name": "Robin Blöhm",
    "gender": "男",
    "country": "Germany",
    "province": "",
    "city": "",
    "result": "6:41.05",
    "competition": "German Nationals 2010",
    "date": "2010-09-11"
  },
  {
    "wcaid": "2008TORR02",
    "name": "Víctor Torrecilla Chicote",
    "gender": "男",
    "country": "Spain",
    "province": "",
    "city": "",
    "result": "7:47.55",
    "competition": "Barcelona Rubik's Summer Open 2010",
    "date": "2010-07-09"
  },
  {
    "wcaid": "2007ORTI01",
    "name": "Daniel Ortiga Villatoro",
    "gender": "男",
    "country": "Spain",
    "province": "",
    "city": "",
    "result": "18:22.00",
    "competition": "Barcelona Rubik's Summer Open 2010",
    "date": "2010-07-09"
  },
  {
    "wcaid": "2010ESTE01",
    "name": "Arnau Esteller Beltrán",
    "gender": "男",
    "country": "Spain",
    "province": "",
    "city": "",
    "result": "23:28.00",
    "competition": "Barcelona Rubik's Summer Open 2010",
    "date": "2010-07-09"
  },
  {
    "wcaid": "2010PARR01",
    "name": "David Parra Meza",
    "gender": "男",
    "country": "Peru",
    "province": "",
    "city": "",
    "result": "29:00.00",
    "competition": "Barcelona Rubik's Summer Open 2010",
    "date": "2010-07-09"
  },
  {
    "wcaid": "2009HINP01",
    "name": "Pang Pak Hin (彭栢軒)",
    "gender": "男",
    "country": "China",
    "province": "香港",
    "city": "香港",
    "result": "3:57.83",
    "competition": "Guangzhou Big Cubes Competition 2010",
    "date": "2010-07-11"
  },
  {
    "wcaid": "2008ZHAN06",
    "name": "Haixu Zhang (张海旭)",
    "gender": "男",
    "country": "China",
    "province": "广东",
    "city": "珠海",
    "result": "4:16.18",
    "competition": "Guangdong Open 2010",
    "date": "2010-10-03"
  },
  {
    "wcaid": "2009HAOM01",
    "name": "Li Haoming (利浩铭)",
    "gender": "男",
    "country": "China",
    "province": "神手谷",
    "city": "神手谷",
    "result": "5:58.71",
    "competition": "Guangzhou Big Cubes Competition 2010",
    "date": "2010-07-11"
  },
  {
    "wcaid": "2009YINC05",
    "name": "Chengzhi Yin (殷程智)",
    "gender": "男",
    "country": "China",
    "province": "神手谷",
    "city": "神手谷",
    "result": "7:34.43",
    "competition": "Inner Mongolia 2010",
    "date": "2010-07-24"
  },
  {
    "wcaid": "2010CHEN24",
    "name": "Jacob Chenitz",
    "gender": "男",
    "country": "USA",
    "province": "",
    "city": "",
    "result": "7:47.72",
    "competition": "Cat and Mouse 2010",
    "date": "2010-07-17"
  },
  {
    "wcaid": "2008WEHO01",
    "name": "Rudolf Wehofer",
    "gender": "男",
    "country": "Hungary",
    "province": "",
    "city": "",
    "result": "5:24.03",
    "competition": "Austrian Open 2010",
    "date": "2010-07-31"
  },
  {
    "wcaid": "2009WUTI02",
    "name": "Tianzhi Wu (吴天智)",
    "gender": "男",
    "country": "China",
    "province": "神手谷",
    "city": "神手谷",
    "result": "5:04.21",
    "competition": "Inner Mongolia 2010",
    "date": "2010-07-24"
  },
  {
    "wcaid": "2008LOPE03",
    "name": "Gerardo Villa López",
    "gender": "男",
    "country": "Mexico",
    "province": "",
    "city": "",
    "result": "9:00.59",
    "competition": "Guadalajara Open 2010",
    "date": "2010-07-24"
  },
  {
    "wcaid": "2008CAMP01",
    "name": "Pablo Ruiz Campos",
    "gender": "男",
    "country": "Mexico",
    "province": "",
    "city": "",
    "result": "13:02.00",
    "competition": "Guadalajara Open 2010",
    "date": "2010-07-24"
  },
  {
    "wcaid": "2010DATL01",
    "name": "Ronnel Datlag",
    "gender": "男",
    "country": "USA",
    "province": "",
    "city": "",
    "result": "5:23.88",
    "competition": "United States Rubik's Cube Championships 2010",
    "date": "2010-08-06"
  },
  {
    "wcaid": "2009LIAN03",
    "name": "Chester Lian",
    "gender": "男",
    "country": "Malaysia",
    "province": "",
    "city": "",
    "result": "5:49.96",
    "competition": "United States Rubik's Cube Championships 2010",
    "date": "2010-08-06"
  },
  {
    "wcaid": "2009MCLE01",
    "name": "Quentin McLean",
    "gender": "男",
    "country": "USA",
    "province": "",
    "city": "",
    "result": "7:09.97",
    "competition": "United States Rubik's Cube Championships 2010",
    "date": "2010-08-06"
  },
  {
    "wcaid": "2009RATH02",
    "name": "Brandon Rathbun",
    "gender": "男",
    "country": "USA",
    "province": "",
    "city": "",
    "result": "9:29.34",
    "competition": "United States Rubik's Cube Championships 2010",
    "date": "2010-08-06"
  },
  {
    "wcaid": "2009BETK01",
    "name": "Maik Betka",
    "gender": "男",
    "country": "Germany",
    "province": "",
    "city": "",
    "result": "9:20.65",
    "competition": "East German Open 2010",
    "date": "2010-08-14"
  },
  {
    "wcaid": "2010GROS01",
    "name": "Ronald Großmann",
    "gender": "男",
    "country": "Germany",
    "province": "",
    "city": "",
    "result": "12:41.00",
    "competition": "East German Open 2010",
    "date": "2010-08-14"
  },
  {
    "wcaid": "2009KUBO01",
    "name": "Tomoki Kubo (久保友樹)",
    "gender": "男",
    "country": "Japan",
    "province": "",
    "city": "",
    "result": "8:27.19",
    "competition": "Cube Camp in Kanazawa 2010",
    "date": "2010-08-21"
  },
  {
    "wcaid": "2009SKRZ01",
    "name": "Damian Skrzypiec",
    "gender": "男",
    "country": "Poland",
    "province": "",
    "city": "",
    "result": "6:33.57",
    "competition": "Polish Nationals 2010",
    "date": "2010-08-28"
  },
  {
    "wcaid": "2009TOMB01",
    "name": "Korneliusz Tombarkiewicz",
    "gender": "男",
    "country": "Poland",
    "province": "",
    "city": "",
    "result": "14:41.00",
    "competition": "Polish Nationals 2010",
    "date": "2010-08-28"
  },
  {
    "wcaid": "2010KIMB01",
    "name": "Brian Kim",
    "gender": "男",
    "country": "Korea",
    "province": "",
    "city": "",
    "result": "7:32.11",
    "competition": "Australian Nationals 2010",
    "date": "2010-09-04"
  },
  {
    "wcaid": "2009SCHE02",
    "name": "Lucas Scheiper",
    "gender": "男",
    "country": "Germany",
    "province": "",
    "city": "",
    "result": "7:21.63",
    "competition": "V-CUBE Spiel 2010",
    "date": "2010-10-23"
  },
  {
    "wcaid": "2009NAGY03",
    "name": "Kornél Nagy-Borsy",
    "gender": "男",
    "country": "Hungary",
    "province": "",
    "city": "",
    "result": "4:53.41",
    "competition": "European Rubik's Cube Championship 2010",
    "date": "2010-10-01"
  },
  {
    "wcaid": "2008BENY01",
    "name": "András Bényi",
    "gender": "男",
    "country": "Hungary",
    "province": "",
    "city": "",
    "result": "5:20.72",
    "competition": "Hungarian Open 2010",
    "date": "2010-09-03"
  },
  {
    "wcaid": "2010HUFN01",
    "name": "Tassilo Hufnagel",
    "gender": "男",
    "country": "Germany",
    "province": "",
    "city": "",
    "result": "8:05.11",
    "competition": "German Nationals 2010",
    "date": "2010-09-11"
  },
  {
    "wcaid": "2009DOOS01",
    "name": "Marcel Doose",
    "gender": "男",
    "country": "Germany",
    "province": "",
    "city": "",
    "result": "9:40.97",
    "competition": "German Nationals 2010",
    "date": "2010-09-11"
  },
  {
    "wcaid": "2010REHB01",
    "name": "Frederik Rehbach",
    "gender": "男",
    "country": "Germany",
    "province": "",
    "city": "",
    "result": "12:24.00",
    "competition": "German Nationals 2010",
    "date": "2010-09-11"
  },
  {
    "wcaid": "2006ORLA01",
    "name": "Bernett Orlando",
    "gender": "男",
    "country": "India",
    "province": "",
    "city": "",
    "result": "6:18.22",
    "competition": "Shaastra Cube Open 2010",
    "date": "2010-10-01"
  },
  {
    "wcaid": "2009KADU01",
    "name": "Rahul Kadukar",
    "gender": "男",
    "country": "India",
    "province": "",
    "city": "",
    "result": "7:21.15",
    "competition": "Shaastra Cube Open 2010",
    "date": "2010-10-01"
  },
  {
    "wcaid": "2009ZHAN50",
    "name": "Huadong Zhang (张华东)",
    "gender": "男",
    "country": "China",
    "province": "神手谷",
    "city": "神手谷",
    "result": "7:14.03",
    "competition": "Guangdong Open 2010",
    "date": "2010-10-03"
  },
  {
    "wcaid": "2009PUTR06",
    "name": "Janitra Ezra Putra",
    "gender": "男",
    "country": "Indonesia",
    "province": "",
    "city": "",
    "result": "5:31.75",
    "competition": "Jakarta Ceria Open 2010",
    "date": "2010-10-29"
  },
  {
    "wcaid": "2010BODM01",
    "name": "Nicolas Bodmer",
    "gender": "男",
    "country": "Switzerland",
    "province": "",
    "city": "",
    "result": "8:27.44",
    "competition": "Munich Open 2010",
    "date": "2010-10-09"
  },
  {
    "wcaid": "2009LOOS01",
    "name": "Dennis Loose",
    "gender": "男",
    "country": "Germany",
    "province": "",
    "city": "",
    "result": "10:38.00",
    "competition": "V-CUBE Spiel 2010",
    "date": "2010-10-23"
  },
  {
    "wcaid": "2010JNGE01",
    "name": "Steffen Jünger",
    "gender": "男",
    "country": "Germany",
    "province": "",
    "city": "",
    "result": "11:47.00",
    "competition": "V-CUBE Spiel 2010",
    "date": "2010-10-23"
  },
  {
    "wcaid": "2009KONI03",
    "name": "Felix König",
    "gender": "男",
    "country": "Germany",
    "province": "",
    "city": "",
    "result": "11:48.00",
    "competition": "V-CUBE Spiel 2010",
    "date": "2010-10-23"
  },
  {
    "wcaid": "2009DUMO01",
    "name": "Frank Dumont",
    "gender": "男",
    "country": "Germany",
    "province": "",
    "city": "",
    "result": "13:12.00",
    "competition": "V-CUBE Spiel 2010",
    "date": "2010-10-23"
  },
  {
    "wcaid": "2010DEVI01",
    "name": "Cristo Devinco",
    "gender": "男",
    "country": "Indonesia",
    "province": "",
    "city": "",
    "result": "8:46.21",
    "competition": "Jakarta Ceria Open 2010",
    "date": "2010-10-29"
  },
  {
    "wcaid": "2010REYN01",
    "name": "Fathur Reynaldi",
    "gender": "男",
    "country": "Indonesia",
    "province": "",
    "city": "",
    "result": "9:26.55",
    "competition": "Jakarta Ceria Open 2010",
    "date": "2010-10-29"
  },
  {
    "wcaid": "2010BRUC01",
    "name": "Luke Bruce",
    "gender": "男",
    "country": "Australia",
    "province": "",
    "city": "",
    "result": "6:03.86",
    "competition": "Melbourne Cube Day 2010",
    "date": "2010-11-13"
  },
  {
    "wcaid": "2010ZAKH01",
    "name": "Peter Zakharov",
    "gender": "男",
    "country": "Russia",
    "province": "",
    "city": "",
    "result": "8:16.33",
    "competition": "MPEI Open 2010",
    "date": "2010-11-20"
  },
  {
    "wcaid": "2010WANG28",
    "name": "Shengqun Wang (王胜群)",
    "gender": "男",
    "country": "China",
    "province": "神手谷",
    "city": "神手谷",
    "result": "5:18.36",
    "competition": "Beijing No Cubes 2010",
    "date": "2010-11-28"
  },
  {
    "wcaid": "2009QIAO01",
    "name": "Chengcheng Qiao (乔成成)",
    "gender": "男",
    "country": "China",
    "province": "江苏",
    "city": "盐城",
    "result": "9:29.27",
    "competition": "Beijing No Cubes 2010",
    "date": "2010-11-28"
  },
  {
    "wcaid": "2009LUCE01",
    "name": "Gian Sebastian Lucero",
    "gender": "男",
    "country": "Philippines",
    "province": "",
    "city": "",
    "result": "8:12.53",
    "competition": "Cebu Open 2010",
    "date": "2010-12-07"
  },
  {
    "wcaid": "2009LIMD01",
    "name": "Danjick Earvin Lim",
    "gender": "男",
    "country": "Philippines",
    "province": "",
    "city": "",
    "result": "8:20.59",
    "competition": "Cebu Open 2010",
    "date": "2010-12-07"
  },
  {
    "wcaid": "2009BUNP01",
    "name": "Worasil Bunpeam (วรศิลป์ บุญเปี่ยม)",
    "gender": "男",
    "country": "Thailand",
    "province": "",
    "city": "",
    "result": "6:36.31",
    "competition": "Malaysian Cube Open 2010",
    "date": "2010-12-18"
  },
  {
    "wcaid": "2009AZRA01",
    "name": "Mohamad Azraei",
    "gender": "男",
    "country": "Malaysia",
    "province": "",
    "city": "",
    "result": "6:21.28",
    "competition": "Malaysian Cube Open 2010",
    "date": "2010-12-18"
  }
]